README
setup.py
src/m3_license/__init__.py
src/m3_license/api.py
src/m3_license/middleware.py
src/m3_license/models.py
src/m3_license.egg-info/PKG-INFO
src/m3_license.egg-info/SOURCES.txt
src/m3_license.egg-info/dependency_links.txt
src/m3_license.egg-info/not-zip-safe
src/m3_license.egg-info/requires.txt
src/m3_license.egg-info/top_level.txt
src/m3_license/management/__init__.py
src/m3_license/management/commands/__init__.py
src/m3_license/management/commands/license_status.py
test/test_license.py
test/test_manage_command.py
test/test_middleware.py