Metadata-Version: 1.1
Name: m3-license
Version: 0.0.2
Summary: UNKNOWN
Home-page: http://bars-open.ru
Author: BARS Group
Author-email: bars@bars-open.ru
License: UNKNOWN
Keywords: django m3 bars group
Platform: UNKNOWN
Classifier: Intended Audience :: Developers
Classifier: Environment :: Web Environment
Classifier: Natural Language :: Russian
Classifier: Natural Language :: English
Classifier: Operating System :: OS Independent
Classifier: Programming Language :: Python
Classifier: License :: OSI Approved :: MIT License
Classifier: Development Status :: 5 - Production/Stable
